mikoto/__init__.py
mikoto/auth.py
mikoto/schema.py
mikoto_py-0.0.7.dist-info/METADATA
mikoto_py-0.0.7.dist-info/WHEEL
mikoto_py-0.0.7.dist-info/RECORD
