Metadata-Version: 2.1
Name: mikoto-py
Version: 0.0.7
Summary: The Python framework for interacting with Mikoto
License: MIT
Author: TheCactusBlue
Author-email: cactus@mikoto.io
Requires-Python: >=3.8,<4.0
Classifier: License :: OSI Approved :: MIT License
Classifier: Programming Language :: Python :: 3
Classifier: Programming Language :: Python :: 3.8
Classifier: Programming Language :: Python :: 3.9
Classifier: Programming Language :: Python :: 3.10
Classifier: Programming Language :: Python :: 3.11
Requires-Dist: aiohttp (>=3.8.5,<4.0.0)
Requires-Dist: httpx (>=0.25.0,<0.26.0)
Requires-Dist: pydantic (>=2.3.0,<3.0.0)
Requires-Dist: python-socketio (>=5.9.0,<6.0.0)
